Metadata-Version: 2.1
Name: xhj-nameko-dependency
Version: 0.0.1
Summary: xhj nameko dependency
Home-page: UNKNOWN
Author: william.dai
Author-email: daixiang1992@gmail.com
License: MIT
Keywords: xhj nameko
Platform: UNKNOWN
